{
    "products" : [
        {
            "id": 1,
            "title": "HP Laptop 14-DQ0052DX Intel Celeron N4120 4GB RAM, 64GB eMMC, Windows 11 - 685K1UA",
            "image": "https://techmall.com.ng/wp-content/uploads/2024/08/HP-Laptop-14-EP0792-2.png",
            "category": "Laptop",
            "price": 4500,
            "reviews": 112
        },
        {
            "id": 2,
            "title": "24inch LED Monitor with IPS panel and Borderless Design LF24T350FHMXZN  Samsung Levant",
            "image": "https://images.philips.com/is/image/philipsconsumer/c21144b78aff43aab2fab01c00c2c149?$pnglarge$&wid=1250",
            "category": "Monitor",
            "price": 7800,
            "reviews": 524
        },
        {
            "id": 3,
            "title": "Oppo X1 128gb",
            "image": "https://image.oppo.com/content/dam/oppo/common/mkt/v2-2/oppo-a3-pro-5g-en/featured/640_640-purple.png.thumb.webp",
            "category": "Phone",
            "price": 675,
            "reviews": 524
        },
        {
            "id": 4,
            "title": "WH-CH520 Wireless | Headphones | Sony Asia Pacific",
            "image": "https://sony.scene7.com/is/image/sonyglobalsolutions/wh-ch520_Primary_image?$categorypdpnav$&fmt=png-alpha",
            "category": "Headphone",
            "price": 125,
            "reviews": 362
        },
        {
          "id": 1,
          "title": "24inch LED Monitor with IPS panel and Borderless Design LF24T350FHMXZN  Samsung Levant",
          "image": "https://images.samsung.com/is/image/samsung/p6pim/za/lf24t350fhaxxa/gallery/za-t35f-374271-lf24t350fhaxxa-516514409?$650_519_PNG$",  
          "category": "Monitor",
          "price": 7800,
          "reviews": 524
        },
        {
          "id": 2,
          "title": "Dell UltraSharp 27-inch 4K Monitor",
          "image": "https://i.dell.com/is/image/DellContent//content/dam/images/products/electronics-and-accessories/dell/monitors/s-series/s2721qs/s2721qs-cfp-00025lf095-gy.psd?fmt=png-alpha&pscan=auto&scl=1&hei=804&wid=891&qlt=100,1&resMode=sharp2&size=891,804&chrss=full", 
          "category": "Monitor",
          "price": 649,
          "reviews": 890
        },
        {
          "id": 1,
          "title": "HP Laptop 14-DQ0052DX Intel Celeron N4120 4GB RAM, 64GB eMMC, Windows 11 - 685K1UA",
          "image": "https://techmall.com.ng/wp-content/uploads/2024/08/HP-Laptop-14-EP0792-2.png",
          "category": "Laptop",
          "price": 4500,
          "reviews": 112
        },
        {
          "id": 2,
          "title": "24inch LED Monitor with IPS panel and Borderless Design LF24T350FHMXZN  Samsung Levant",
          "image": "https://images.philips.com/is/image/philipsconsumer/c21144b78aff43aab2fab01c00c2c149?$pnglarge$&wid=1250",
          "category": "Monitor",
          "price": 7800,
          "reviews": 524
        },
        {
          "id": 3,
          "title": "Oppo X1 128gb",
          "image": "https://image.oppo.com/content/dam/oppo/common/mkt/v2-2/oppo-a3-pro-5g-en/featured/640_640-purple.png.thumb.webp",
          "category": "Phone",
          "price": 675,
          "reviews": 524
        }
    ]}
